[
  {
    "slug": "anderson",
    "name": "Anderson"
  },
  {
    "slug": "bedford",
    "name": "Bedford"
  },
  {
    "slug": "benton",
    "name": "Benton"
  },
  {
    "slug": "bledsoe",
    "name": "Bledsoe"
  },
  {
    "slug": "blount",
    "name": "Blount"
  },
  {
    "slug": "bradley",
    "name": "Bradley"
  },
  {
    "slug": "campbell",
    "name": "Campbell"
  },
  {
    "slug": "cannon",
    "name": "Cannon"
  },
  {
    "slug": "carroll",
    "name": "Carroll"
  },
  {
    "slug": "carter",
    "name": "Carter"
  },
  {
    "slug": "cheatham",
    "name": "Cheatham"
  },
  {
    "slug": "chester",
    "name": "Chester"
  },
  {
    "slug": "claiborne",
    "name": "Claiborne"
  },
  {
    "slug": "clay",
    "name": "Clay"
  },
  {
    "slug": "cocke",
    "name": "Cocke"
  },
  {
    "slug": "coffee",
    "name": "Coffee"
  },
  {
    "slug": "crockett",
    "name": "Crockett"
  },
  {
    "slug": "cumberland",
    "name": "Cumberland"
  },
  {
    "slug": "davidson",
    "name": "Davidson"
  },
  {
    "slug": "decatur",
    "name": "Decatur"
  },
  {
    "slug": "dekalb",
    "name": "DeKalb"
  },
  {
    "slug": "dickson",
    "name": "Dickson"
  },
  {
    "slug": "dyer",
    "name": "Dyer"
  },
  {
    "slug": "fayette",
    "name": "Fayette"
  },
  {
    "slug": "fentress",
    "name": "Fentress"
  },
  {
    "slug": "franklin",
    "name": "Franklin"
  },
  {
    "slug": "gibson",
    "name": "Gibson"
  },
  {
    "slug": "giles",
    "name": "Giles"
  },
  {
    "slug": "grainger",
    "name": "Grainger"
  },
  {
    "slug": "greene",
    "name": "Greene"
  },
  {
    "slug": "grundy",
    "name": "Grundy"
  },
  {
    "slug": "hamblen",
    "name": "Hamblen"
  },
  {
    "slug": "hamilton",
    "name": "Hamilton"
  },
  {
    "slug": "hancock",
    "name": "Hancock"
  },
  {
    "slug": "hardeman",
    "name": "Hardeman"
  },
  {
    "slug": "hardin",
    "name": "Hardin"
  },
  {
    "slug": "hawkins",
    "name": "Hawkins"
  },
  {
    "slug": "haywood",
    "name": "Haywood"
  },
  {
    "slug": "henderson",
    "name": "Henderson"
  },
  {
    "slug": "henry",
    "name": "Henry"
  },
  {
    "slug": "hickman",
    "name": "Hickman"
  },
  {
    "slug": "houston",
    "name": "Houston"
  },
  {
    "slug": "humphreys",
    "name": "Humphreys"
  },
  {
    "slug": "jackson",
    "name": "Jackson"
  },
  {
    "slug": "jefferson",
    "name": "Jefferson"
  },
  {
    "slug": "johnson",
    "name": "Johnson"
  },
  {
    "slug": "knox",
    "name": "Knox"
  },
  {
    "slug": "lake",
    "name": "Lake"
  },
  {
    "slug": "lauderdale",
    "name": "Lauderdale"
  },
  {
    "slug": "lawrence",
    "name": "Lawrence"
  },
  {
    "slug": "lewis",
    "name": "Lewis"
  },
  {
    "slug": "lincoln",
    "name": "Lincoln"
  },
  {
    "slug": "loudon",
    "name": "Loudon"
  },
  {
    "slug": "macon",
    "name": "Macon"
  },
  {
    "slug": "madison",
    "name": "Madison"
  },
  {
    "slug": "marion",
    "name": "Marion"
  },
  {
    "slug": "marshall",
    "name": "Marshall"
  },
  {
    "slug": "maury",
    "name": "Maury"
  },
  {
    "slug": "mcminn",
    "name": "McMinn"
  },
  {
    "slug": "mcnairy",
    "name": "McNairy"
  },
  {
    "slug": "meigs",
    "name": "Meigs"
  },
  {
    "slug": "monroe",
    "name": "Monroe"
  },
  {
    "slug": "montgomery",
    "name": "Montgomery"
  },
  {
    "slug": "moore",
    "name": "Moore"
  },
  {
    "slug": "morgan",
    "name": "Morgan"
  },
  {
    "slug": "obion",
    "name": "Obion"
  },
  {
    "slug": "overton",
    "name": "Overton"
  },
  {
    "slug": "perry",
    "name": "Perry"
  },
  {
    "slug": "pickett",
    "name": "Pickett"
  },
  {
    "slug": "polk",
    "name": "Polk"
  },
  {
    "slug": "putnam",
    "name": "Putnam"
  },
  {
    "slug": "rhea",
    "name": "Rhea"
  },
  {
    "slug": "roane",
    "name": "Roane"
  },
  {
    "slug": "robertson",
    "name": "Robertson"
  },
  {
    "slug": "rutherford",
    "name": "Rutherford"
  },
  {
    "slug": "scott",
    "name": "Scott"
  },
  {
    "slug": "sequatchie",
    "name": "Sequatchie"
  },
  {
    "slug": "sevier",
    "name": "Sevier"
  },
  {
    "slug": "shelby",
    "name": "Shelby"
  },
  {
    "slug": "smith",
    "name": "Smith"
  },
  {
    "slug": "stewart",
    "name": "Stewart"
  },
  {
    "slug": "sullivan",
    "name": "Sullivan"
  },
  {
    "slug": "sumner",
    "name": "Sumner"
  },
  {
    "slug": "tipton",
    "name": "Tipton"
  },
  {
    "slug": "trousdale",
    "name": "Trousdale"
  },
  {
    "slug": "unicoi",
    "name": "Unicoi"
  },
  {
    "slug": "union",
    "name": "Union"
  },
  {
    "slug": "van-buren",
    "name": "Van Buren"
  },
  {
    "slug": "warren",
    "name": "Warren"
  },
  {
    "slug": "washington",
    "name": "Washington"
  },
  {
    "slug": "wayne",
    "name": "Wayne"
  },
  {
    "slug": "weakley",
    "name": "Weakley"
  },
  {
    "slug": "white",
    "name": "White"
  },
  {
    "slug": "williamson",
    "name": "Williamson"
  },
  {
    "slug": "wilson",
    "name": "Wilson"
  }
]